openvoid/__init__.py
openvoid/async_client.py
openvoid/client.py
openvoid/client_base.py
openvoid/constants.py
openvoid/exceptions.py
openvoid/models/__init__.py
openvoid/models/chat_completion.py
openvoid/models/common.py
openvoid/models/models.py
openvoid/py.typed
openvoid-0.0.1.dist-info/LICENSE
openvoid-0.0.1.dist-info/METADATA
openvoid-0.0.1.dist-info/WHEEL
openvoid-0.0.1.dist-info/RECORD
