Metadata-Version: 2.1
Name: openvoid
Version: 0.0.1
Summary: 
Author: Anthony
Author-email: anthony@openvoid.ai
Requires-Python: >=3.8,<4.0
Classifier: Programming Language :: Python :: 3
Classifier: Programming Language :: Python :: 3.8
Classifier: Programming Language :: Python :: 3.9
Classifier: Programming Language :: Python :: 3.10
Classifier: Programming Language :: Python :: 3.11
Classifier: Programming Language :: Python :: 3.12
Requires-Dist: httpx (>=0.25.2,<0.26.0)
Requires-Dist: orjson (>=3.9.10,<4.0.0)
Requires-Dist: pydantic (>=2.5.2,<3.0.0)
